
{
	"code":100000,
	"results":{
		"axisxData":[
			{
				"name":"白色彩电",
				"type":"分类",
				"length":7,
				"lev":3,
				"list":[
					{
						
						"name":"第一季度",
						"type":"季节",
						"length":4,
						"lev":2
					},
					{
						
						"name":"促销",
						"type":"促销方式",
						"length":1,
						"lev":1,
						"val":[1,2,3,4,5,6,7,8,9,10,11,12,13]
					}
				]
			},
			{
				"name":"白色彩电",
				"length":7,
				"type":"分类",
				"lev":3,
				"list":[
					{
						
						"name":"第一季度",
						"type":"季节",
						"length":4,
						"lev":2
					},
					{
						
						"name":"正常",
						"length":1,
						"lev":1,
						"type":"促销方式",
						"val":[1,2,3,4,5,6,7,8,9,10,11,12,13]
					}
				]
			},
			{
				"name":"白色彩电",
				"length":7,
				"lev":3,
				"type":"分类",
				"list":[
					{
						
						"name":"第一季度",
						"type":"季节",
						"length":4,
						"lev":2
					},
					{
						
						"name":"降价",
						"length":1,
						"lev":1,
						"type":"促销方式",
						"val":[1,2,3,4,5,6,7,8,9,10,11,12,13]
					}
				]
			},

			{
				"name":"白色彩电",
				"length":7,
				"lev":3,
				"type":"分类",
				"list":[
					{
						
						"name":"第一季度",
						"type":"季节",
						"length":4,
						"lev":2
					},
					{
						
						"name":"小计",
						"length":1,
						"lev":1,
						"type":"促销方式",
						"val":[1,2,3,4,5,6,7,8,9,10,11,12,13]
					}
				]
			},

			
			{
				"name":"白色彩电",
				"length":7,
				"lev":3,
				"type":"分类",
				"list":[
					{
						
						"name":"第二季度",
						"type":"季节",
						"length":2,
						"lev":2
					},
					{
						
						"name":"正常",
						"length":1,
						"lev":1,
						"type":"促销方式",
						"val":[1,2,3,4,5,6,7,8,9,10,11,12,13]
					}
				]
			},
			
			{
				"name":"白色彩电",
				"length":7,
				"lev":3,
				"type":"分类",
				"list":[
					{
						
						"name":"第二季度",
						"type":"季节",
						"length":2,
						"lev":2
					},
					{
						
						"name":"小计",
						"length":1,
						"lev":1,
						"type":"促销方式",
						"val":[1,2,3,4,5,6,7,8,9,10,11,12,13]
					}
				]
			},

			
			{
				"name":"白色彩电",
				"length":6,
				"lev":3,
				"type":"分类",
				"list":[
					{
						
						"name":"小计",
						"type":"季节",
						"length":1,
						"lev":2,
						"val":[1,2,3,4,5,6,7,8,9,10,11,12,13]
					}
				]
			},


			
			{
				"name":"黑色彩电",
				"type":"分类",
				"length":3,
				"lev":3,
				"list":[
					{
						
						"name":"第一季度",
						"type":"季节",
						"length":2,
						"lev":2
					},
					{
						
						"name":"促销",
						"length":1,
						"lev":1,
						"type":"促销方式",
						"val":[1,2,3,4,5,6,7,8,9,10,11,12,13]
					}
				]
			},
			
			{
				"name":"黑色彩电",
				"type":"分类",
				"length":3,
				"lev":3,
				"list":[
					{
						
						"name":"第一季度",
						"type":"季节",
						"length":2,
						"lev":2
					},
					{
						
						"name":"小计",
						"length":1,
						"lev":1,
						"type":"促销方式",
						"val":[1,2,3,4,5,6,7,8,9,10,11,12,13]
					}
				]
			},
			{
				"name":"黑色彩电",
				"type":"分类",
				"length":3,
				"lev":3,
				"list":[
					{
						
						"name":"小计",
						"type":"季节",
						"length":1,
						"lev":2,
						"val":[1,2,3,4,5,6,7,8,9,10,11,12,13]
					}
				]
			}
		],
		"axisyData":[
			[
				{
					"name":"销售量",
					"length":6,
					"lev":3
				},
				{
					"name":"环比增长",
					"length":7,
					"lev":3
				}
			],
			[
				{
					"name":"小型商场",
					"length":"3",
					"lev":2
				},
				{
					"name":"中型商场",
					"length":"1",
					"lev":2
				},
				{
					"name":"大型商场",
					"length":"1",
					"lev":2
				},
				{
					"name":"小计",
					"length":"1",
					"lev":2
				},
				{
					"name":"小型商场",
					"length":"3",
					"lev":2
				},
				{
					"name":"中型商场",
					"length":"1",
					"lev":2
				},
				{
					"name":"大型商场",
					"length":"3",
					"lev":2
				}
			],
			[
				{
					"name":"test",
					"length":"1",
					"lev":1
				},
				{
					"name":"test",
					"length":"1",
					"lev":1
				},
				{
					"name":"test",
					"length":"1",
					"lev":1
				},
				{
					"name":"test",
					"length":"1",
					"lev":1
				},
				{
					"name":"test",
					"length":"1",
					"lev":1
				},
				{
					"name":"test",
					"length":"1",
					"lev":1
				},
				{
					"name":"test",
					"length":"1",
					"lev":1
				},
				{
					"name":"test",
					"length":"1",
					"lev":1
				},
				{
					"name":"test",
					"length":"1",
					"lev":1
				},
				{
					"name":"test",
					"length":"1",
					"lev":1
				},
				{
					"name":"test",
					"length":"1",
					"lev":1
				},
				{
					"name":"test",
					"length":"1",
					"lev":1
				}
			]
		]
	}
}